{"type":"PR","pr":{"number":5,"head":"46d2ccc71155b18d747fa40f8b141e1812fcdbb1"},"user":"jamesETF","status":"draft","branch":"cms/2019-08-15-post9","collection":"posts","title":"The Rise of French Bulldog Theft and What you need to Know and Solve","description":"As French bulldogs are at high risk of being stolen and the French bulldog theft has been on the increase, it's time to take immediate precaution measures.","objects":{"entry":{"path":"_posts/2019-08-15-post9.md","sha":"fc09dc2be0c1aea49ed83014fc4e231d5b0fc8d4"},"files":[]},"timeStamp":"2020-02-13T00:03:32.731Z"}